betterfit/__init__.py
betterfit/dataset.py
betterfit/fits/__init__.py
betterfit/fits/fit.py
betterfit/fits/linear.py
betterfit/py.typed
betterfit/types.py
betterfit-0.0.2a3.dist-info/LICENSE
betterfit-0.0.2a3.dist-info/METADATA
betterfit-0.0.2a3.dist-info/WHEEL
betterfit-0.0.2a3.dist-info/RECORD
